mcvqoe/tvo/__init__.py
mcvqoe/tvo/version.py
mcvqoe/tvo/volume_adjust.py
mcvqoe/tvo/volume_adjust_eval.py
mcvqoe/tvo/volume_adjust_hw_test.py
mcvqoe/tvo/audio_clips/Vol_Set_F1.wav
mcvqoe/tvo/audio_clips/Vol_Set_F3.wav
mcvqoe/tvo/audio_clips/Vol_Set_M3.wav
mcvqoe/tvo/audio_clips/Vol_Set_M4.wav
mcvqoe_tvo-2.0.1.dist-info/METADATA
mcvqoe_tvo-2.0.1.dist-info/WHEEL
mcvqoe_tvo-2.0.1.dist-info/entry_points.txt
mcvqoe_tvo-2.0.1.dist-info/top_level.txt
mcvqoe_tvo-2.0.1.dist-info/RECORD
