Metadata-Version: 2.1
Name: mcvqoe-tvo
Version: 2.0.1
Summary: Measurement code for access time
Home-page: https://github.com/usnistgov/MCV-QOE-TVO
Author: PSCR
Author-email: PSCR@PSCR.gov
License: NIST software License
Classifier: Programming Language :: Python :: 3
Classifier: License :: Public Domain
Classifier: Operating System :: OS Independent
Requires-Python: >=3.6
Requires-Dist: mcvqoe-base
Requires-Dist: scipy
